flutter_launcher/__main__.py
flutter_launcher/common.py
flutter_launcher/dart.py
flutter_launcher/flutter.py
flutter_launcher/flutter_dev.py
flutter_launcher/shared.py
flutter_launcher-2025.6.18.1.dist-info/METADATA
flutter_launcher-2025.6.18.1.dist-info/WHEEL
flutter_launcher-2025.6.18.1.dist-info/entry_points.txt
flutter_launcher-2025.6.18.1.dist-info/licenses/LICENSE
flutter_launcher-2025.6.18.1.dist-info/RECORD
