Metadata-Version: 2.4
Name: flutter-launcher
Version: 2025.6.18.1
Summary: launcher script for flutter
License-File: LICENSE
Requires-Python: >=3.11
